ndex2/__init__.py
ndex2/client.py
ndex2/constants.py
ndex2/cx2.py
ndex2/exceptions.py
ndex2/niceCxInterface.py
ndex2/nice_cx_network.py
ndex2/util.py
ndex2/version.py
ndex2cx/__init__.py
ndex2cx/nice_cx_builder.py
ndex2cx/parallelCX.py
ndex2-3.11.0.dist-info/LICENSE.txt
ndex2-3.11.0.dist-info/METADATA
ndex2-3.11.0.dist-info/WHEEL
ndex2-3.11.0.dist-info/top_level.txt
ndex2-3.11.0.dist-info/RECORD
