Metadata-Version: 2.1
Name: ndex2
Version: 3.11.0
Summary: Nice CX Python includes a client and a data model.
Home-page: https://github.com/ndexbio/ndex2-client
Author: The NDEx Project
Author-email: contact@ndexbio.org
License: BSD
Keywords: network analysis biology
Classifier: Development Status :: 5 - Production/Stable
Classifier: Intended Audience :: Science/Research
Classifier: Topic :: Scientific/Engineering :: Information Analysis
Classifier: Topic :: Scientific/Engineering :: Bio-Informatics
Classifier: Topic :: Scientific/Engineering :: Medical Science Apps.
Classifier: License :: OSI Approved :: BSD License
Classifier: Programming Language :: Python :: 3.5
Classifier: Programming Language :: Python :: 3.6
Classifier: Programming Language :: Python :: 3.7
Classifier: Programming Language :: Python :: 3.8
Classifier: Programming Language :: Python :: 3.9
Classifier: Programming Language :: Python :: 3.10
Classifier: Programming Language :: Python :: 3.11
Classifier: Programming Language :: Python :: 3.12
License-File: LICENSE.txt
Requires-Dist: six
Requires-Dist: ijson
Requires-Dist: requests
Requires-Dist: requests-toolbelt
Requires-Dist: networkx
Requires-Dist: urllib3 >=1.16
Requires-Dist: pandas
Requires-Dist: numpy
Requires-Dist: enum34 ; python_version < "3.4"
Requires-Dist: enum ; python_version == "2.6" or python_version == "2.7"
